{
  "Query": "disable services on startup in ubuntu",
  "Answers": [
    {
      "Command": "update-rc.d",
      "MP Summary": "install and remove System-V style init script links",
      "Most Similar TLDR Task": "Disable a service",
      "Most Similar TLDR Script": "update-rc.d {{mysql}} disable",
      "Top-3 Similar Questions": [
        "so_15119945: How can I disable the lighttpd daemon on startup in Ubuntu",
        "au_160818: Having tried differen ways but none worked - How do I disable a service from auto-start at boot in Ubuntu?",
        "au_343258: How do I disable mini-http on boot?"
      ],
      "Top-3 Scripts": [
        "so_15119945: sudo update-rc.d -f lighttpd remove",
        "au_160818: update-rc.d -f service_name remove",
        "au_343258: sudo update-rc.d mini-httpd disable\n\nsudo update-rc.d remove\n\nsudo update-rc.d mini-httpd defaults"
      ],
      "Explanations about Options": {
        "-f": "Force removal of symlinks even if /etc/init.d/name still exists."
      }
    },
    {
      "Command": "service",
      "MP Summary": "run a System V init script",
      "Most Similar TLDR Task": "Start/Stop/Restart/Reload service (start/stop should always be available)",
      "Most Similar TLDR Script": "service {{service_name}} {{start|stop|restart|reload}}",
      "Top-3 Similar Questions": [
        "ul_108038: Why can't I disable some of the services in system-config-services?",
        "au_590464: How to disable webmin start on boot on Ubuntu?",
        "ul_128267: Disable iptables service on CentOS"
      ],
      "Top-3 Scripts": [
        "ul_108038: ",
        "au_590464: sudo service webmin start",
        "ul_128267: service iptables status"
      ],
      "Explanations about Options": {}
    },
    {
      "Command": "apt-get",
      "MP Summary": "APT package handling utility - command-line interface",
      "Most Similar TLDR Task": "Remove a package and its configuration files",
      "Most Similar TLDR Script": "apt-get purge {{package}}",
      "Top-3 Similar Questions": [
        "au_1369461: How to disable Middle Mouse Paste on Ubuntu automatically on startup",
        "su_266040: How do you disable an upstart service in ubuntu 10.10?",
        "au_413028: Find and disable unnecessary services in Ubuntu 12.04"
      ],
      "Top-3 Scripts": [
        "au_1369461: sudo apt-get install xsel",
        "su_266040: apt-get install chkconfig",
        "au_413028: sudo apt-get install rcconf\nsudo rcconf\n\nsudo apt-get install bum\ngksu  bum"
      ],
      "Explanations about Options": {}
    },
    {
      "Command": "apt",
      "MP Summary": "command-line interface",
      "Most Similar TLDR Task": "Install a package, or update it to the latest available version",
      "Most Similar TLDR Script": "sudo apt install {{package}}",
      "Top-3 Similar Questions": [
        "ul_315502: How to disable `apt-daily.service` on Ubuntu cloud VM image?",
        "ul_667453: How to disable telnet on a Debian 11",
        "au_1335453: How can I disable hwe-support on ubuntu 18.04?"
      ],
      "Top-3 Scripts": [
        "ul_315502: ",
        "ul_667453: sudo apt purge '*telnetd*'",
        "au_1335453: sudo apt install --install-recommends linux-generic\n\nsudo apt install --install-recommends linux-modules-nvidia-NNN-generic\n\nsudo apt remove --purge linux-generic-hwe-20.04 linux-oem-20.04 linux-hwe-* linux-oem-* linux-modules-5.1* linux-modules-5.8.0-* linux-modules-5.6.0-*"
      ],
      "Explanations about Options": {}
    },
    {
      "Command": "systemctl",
      "MP Summary": "Control the systemd system and service manager",
      "Most Similar TLDR Task": "Enable/Disable a unit to be started on bootup",
      "Most Similar TLDR Script": "systemctl enable/disable {{unit}}",
      "Top-3 Similar Questions": [
        "ul_108038: Why can't I disable some of the services in system-config-services?",
        "au_1218013: How to disable unnecessary services starting at boot in Ubuntu 18.04?",
        "su_1596206: How can I disable datadog agent from starting on system boot without disable/uninstall on Ubuntu?"
      ],
      "Top-3 Scripts": [
        "ul_108038: ",
        "au_1218013: sudo systemctl disable",
        "su_1596206: sudo systemctl stop datadog-agent\n\nsudo systemctl disable datadog-agent"
      ],
      "Explanations about Options": {}
    }
  ]
}