{
  "Query": "Terminal command to set audio volume?",
  "Answers": [
    {
      "Command": "pactl",
      "MP Summary": "Control a running PulseAudio sound server",
      "Most Similar TLDR Task": "Set the volume of sink 1 to 75%",
      "Most Similar TLDR Script": "pactl set-sink-volume {{1}} {{0.75}}",
      "Top-3 Similar Questions": [
        "au_1038490: How do you set a default audio output device in Ubuntu?",
        "au_63599: Configuring HDMI Audio via command line"
      ],
      "Top-3 Scripts": [
        "au_1038490: pactl set default sink\n\npactl list short sinks\n\npactl set-default-sink <Your_Device_Name>\n\npactl set-default-sink 'Your-Device-Name'",
        "au_63599: pactl set-card-profile 0 output:hdmi-audio"
      ],
      "Explanations about Options": {}
    },
    {
      "Command": "amixer",
      "MP Summary": "command-line mixer for ALSA soundcard driver",
      "Most Similar TLDR Task": "Turn down the master volume by 10%",
      "Most Similar TLDR Script": "amixer -D pulse sset Master {{10%-}}",
      "Top-3 Similar Questions": [
        "ul_32206: Set volume from terminal",
        "so_19174770: Setting system volume in a bash script (in linux)",
        "su_317296: setting audio balance from command line"
      ],
      "Top-3 Scripts": [
        "ul_32206: # Gets a list of simple mixer controls\n$ amixer scontrols\n\n$ amixer sset 'Master' 50%",
        "so_19174770: amixer set Master 50%     # set absolute\namixer set Master 2dB+    # set relative\namixer set Master unmute",
        "su_317296: amixer sset Master 80%,20%"
      ],
      "Explanations about Options": {}
    },
    {
      "Command": "set",
      "MP Summary": "set or unset options and positional parameters",
      "Most Similar TLDR Task": "Notify of job termination immediately",
      "Most Similar TLDR Script": "set -b",
      "Top-3 Similar Questions": [
        "so_19174770: Setting system volume in a bash script (in linux)",
        "so_46296002: Set Linux master volume from Qt application",
        "au_1038490: How do you set a default audio output device in Ubuntu?"
      ],
      "Top-3 Scripts": [
        "so_19174770: amixer set Master 50%     # set absolute\namixer set Master 2dB+    # set relative\namixer set Master unmute",
        "so_46296002: QProcess::startDetached(\"amixer set Master 70%\")",
        "au_1038490: pactl set default sink"
      ],
      "Explanations about Options": {}
    },
    {
      "Command": "apt-get",
      "MP Summary": "APT package handling utility - command-line interface",
      "Most Similar TLDR Task": "Remove a package and its configuration files",
      "Most Similar TLDR Script": "apt-get purge {{package}}",
      "Top-3 Similar Questions": [
        "au_1123710: How to set the title in Terminal"
      ],
      "Top-3 Scripts": [
        "au_1123710: sudo apt-get install mate-terminal"
      ],
      "Explanations about Options": {}
    },
    {
      "Command": "xbacklight",
      "MP Summary": "adjust backlight brightness using RandR extension",
      "Most Similar TLDR Task": "Get the current screen brightness as a percentage",
      "Most Similar TLDR Script": "xbacklight",
      "Top-3 Similar Questions": [
        "so_25588367: How to control backlight by terminal command"
      ],
      "Top-3 Scripts": [
        "so_25588367: xbacklight -inc 20     # increase backlight by 20%\n xbacklight -dec 30     # decrease by 30%\n xbacklight -set 80     # set to 80% of max value\n xbacklight -get        # get the current level"
      ],
      "Explanations about Options": {
        "-dec": "Decreases brightness by the specified amount.",
        "-get": "Print out the current backlight brightness of each output with such a control. The\n brightness is represented as a percentage of the maximum brightness supported.",
        "-set": "Sets each backlight brightness to the specified level.",
        "-inc": "Increases brightness by the specified amount."
      }
    }
  ]
}