{
    "Answers": [
        {
            "Command": "rmdir",
            "Explanations about Options": {},
            "MP Summary": "remove empty directories",
            "Most Similar TLDR Script": "rmdir {{path/to/directory}}",
            "Most Similar TLDR Task": "Remove directory, provided it is empty. Use `rm -r` to remove non-empty directories",
            "Top-3 Scripts": [
                "so_61573115: PS> 'rm', 'rmdir', 'rd' | Get-Command\n\nCommandType     Name                                               Version    Source\n-----------     ----                                               -------    ------\nAlias           rm -> Remove-Item\nAlias           rmdir -> Remove-Item\nAlias           rd -> Remove-Item",
                "so_51498246: Get-Help rmdir"
            ],
            "Top-3 Similar Questions": [
                "so_61573115: \"rm -rf\" equivalent for Windows PowerShell?",
                "so_51498246: Equivalent of /? for cmd commands in powershell"
            ]
        },
        {
            "Command": "mv",
            "Explanations about Options": {
                "-f(C)": "After word splitting, unless the -f option has been set (see The Set Builtin), Bash scans each word for the characters ‘*’, ‘?’, and ‘[’.",
                "-f(M)": "do not prompt before overwriting",
                "-i(M)": "prompt before overwrite"
            },
            "MP Summary": "move (rename) files",
            "Most Similar TLDR Script": "mv -f {{source}} {{target}}",
            "Most Similar TLDR Task": "Do not prompt for confirmation before overwriting existing files",
            "Top-3 Scripts": [
                "ul_185891: ls -al | grep -v '^d' | xargs -I {} mv {} mysubdir\n\nls -a | while read ITEM; do test ! -d \"$ITEM\" && mv \"$ITEM\" mysubdir; done",
                "ul_532337: find \"$d\" -type f -exec mv -i {} \"$d\" \\;\n\nexport d; find \"$d\" -type f -exec sh -c 'exec mv -i \"$@\" \"$d\"' sh {} +",
                "so_37946069: mv /mydir/$week\\_.* /mydir/week$week;\n#                ^^\n\nmv /mydir/$week\\_* /mydir/week$week;\n#                ^\n\nmv /mydir/${week}_* /mydir/week$week;\n#          ^    ^ ^\n\nfor file in <matching condition>; do\n     mv \"$file\" /another/dir\ndone\n\nfor file in ${week}_*; do\n   mv \"$file\" /mydir/week\"${week}\"/\ndone"
            ],
            "Top-3 Similar Questions": [
                "ul_185891: linux/bash equivalent of mv -t",
                "ul_532337: macOS/bash equivalent of mv -t",
                "so_37946069: Can't use $myvar_.* to mv files starting with $myvar_"
            ]
        },
        {
            "Command": "bash",
            "Explanations about Options": {
                "-c(C)": "The Bash equivalent is \"bash -c <command>\"."
            },
            "MP Summary": "GNU Bourne-Again SHell",
            "Most Similar TLDR Script": "bash -c \"{{command}}\"",
            "Most Similar TLDR Task": "Execute a command",
            "Top-3 Scripts": [
                "su_860833: bash -c <command>",
                "au_986635: man bash"
            ],
            "Top-3 Similar Questions": [
                "su_860833: What's the Bash equivalent of \"cmd /c\"",
                "au_986635: How to exclude a folder when using the mv command"
            ]
        },
        {
            "Command": "view",
            "Explanations about Options": {},
            "MP Summary": "text editors",
            "Most Similar TLDR Script": "view {{file}}",
            "Most Similar TLDR Task": "Open a file",
            "Top-3 Scripts": [],
            "Top-3 Similar Questions": [
                "so_51498246: Equivalent of /? for cmd commands in powershell"
            ]
        },
        {
            "Command": "cp",
            "Explanations about Options": {
                "-p(M)": "same as --preserve=mode , ownership , timestamps",
                "-r(M)": "copy directories recursively"
            },
            "MP Summary": "copy files and directories",
            "Most Similar TLDR Script": "cp -r {{path/to/source_directory}} {{path/to/target_directory}}",
            "Most Similar TLDR Task": "Recursively copy a directory's contents to another location (if the destination exists, the directory is copied inside it)",
            "Top-3 Scripts": [
                "so_42559480: cp -rp /source.file /destination.file",
                "au_823623: #!/bin/sh\n\nfind . -maxdepth 1 -name \\*.old -type f -printf \"deleting %P\\n\" -delete\nfind . -maxdepth 1 -type f -printf \"copying %P to %P.old\\n\" -exec cp '{}' '{}.old' \\;\n\n-exec cp"
            ],
            "Top-3 Similar Questions": [
                "so_42559480: Moving a file in terminal using mv",
                "ul_537518: Bash copy command not working after file rename",
                "au_823623: rm works on command line but not in script"
            ]
        }
    ],
    "Query": "equivalent of rm and mv in windows .cmd"
}