{
    "Answers": [
        {
            "Command": "wc",
            "Explanations about Options": {
                "-w(M)": "print the word counts"
            },
            "MP Summary": "print newline, word, and byte counts for each file",
            "Most Similar TLDR Script": "wc -w {{file}}",
            "Most Similar TLDR Task": "Count words in file",
            "Top-3 Scripts": [
                "so_38160: cpus=$( ls -d /sys/devices/system/cpu/cpu[[:digit:]]* | wc -w )\n\nfind . -name \\*.pdf | xargs --max-args=1 --max-procs=$cpus  pdf2ps",
                "so_20201226: echo '1, 2, 3, 4, 5' | wc -w\n\nwhile read line; do echo $line | wc -w; done < your_file\n\necho '1,2,3,4,5' | tr ',' ' ' | wc -w\n\nwhile read line; do echo $line | tr ',' ' ' | wc -w; done < your_file"
            ],
            "Top-3 Similar Questions": [
                "so_38160: Parallelize Bash script with maximum number of processes",
                "so_20201226: counting number of words in linux"
            ]
        },
        {
            "Command": "ulimit",
            "Explanations about Options": {},
            "MP Summary": "set or report file size limit",
            "Most Similar TLDR Script": "ulimit -u 30",
            "Most Similar TLDR Task": "Set max per-user process limit",
            "Top-3 Scripts": [
                "so_344203: ulimit/getrlimit",
                "su_376532: ulimit -u",
                "so_46100247: [root@llg00amn ~]# ulimit -u\n120996\n[root@llg00amn ~]# docker run -ti debian /bin/bash\nroot@5668a7acb957:/# ulimit -u\nunlimited"
            ],
            "Top-3 Similar Questions": [
                "so_29605502: Maximum number of children processes on Linux",
                "so_344203: Maximum number of threads per process in Linux?",
                "su_376532: Does GNU/Linux counts processes and threads together when I limit their number?"
            ]
        },
        {
            "Command": "nproc",
            "Explanations about Options": {},
            "MP Summary": "print the number of processing units available",
            "Most Similar TLDR Script": "nproc",
            "Most Similar TLDR Task": "Display the number of available processing units",
            "Top-3 Scripts": [],
            "Top-3 Similar Questions": [
                "su_376532: Does GNU/Linux counts processes and threads together when I limit their number?"
            ]
        },
        {
            "Command": "cpulimit",
            "Explanations about Options": {
                "--limit(M)": "percentage of CPU allowed from 1 up. Usually 1 - 100, but can be higher on multi-\n core CPUs. (mandatory)",
                "--pid(M)": "pid of the process"
            },
            "MP Summary": "limits the CPU usage of a process",
            "Most Similar TLDR Script": "cpulimit --pid {{1234}} --limit {{25%}}",
            "Most Similar TLDR Task": "Limit an existing process with PID 1234 to only use 25% of the CPU",
            "Top-3 Scripts": [],
            "Top-3 Similar Questions": [
                "ul_168978: Limit maximum number of concurrent scp processes running on a host"
            ]
        },
        {
            "Command": "seq",
            "Explanations about Options": {
                "-f(M)": "use printf style floating-point FORMAT"
            },
            "MP Summary": "print a sequence of numbers",
            "Most Similar TLDR Script": "seq -f \"%04g\" 5 3 20",
            "Most Similar TLDR Task": "Format output width to a minimum of 4 digits padding with zeros as necessary",
            "Top-3 Scripts": [
                "so_17236456: for ip in $(seq 1 255);do\n  (<whatever you did with $ip in the subshell here, do with $network.$ip instead >) &\n  if (( $ip % 10 == 0 )); then wait; fi\ndone\nwait"
            ],
            "Top-3 Similar Questions": [
                "so_17236456: Limiting the number of subshells spawned"
            ]
        }
    ],
    "Query": "Maximum number of processes in linux"
}