{
    "Answers": [
        {
            "Command": "pkill",
            "Explanations about Options": {
                "-9(C)": "To kill all the processes that you have the permission to kill, simply run the command .  \"kill -15 -1\" or \"kill -9 -1\" depending on the desired behavior (use \"man kill\" for details).",
                "-f(M)": "The pattern is normally only matched against the process name. When -f is set, the\n full command line is used.",
                "-u(M)": "Only match processes whose effective user ID is listed. Either the numerical or\n symbolical value may be used.",
                "-x(M)": "Only match processes whose names (or command line if -f is specified) exactly match\n the pattern."
            },
            "MP Summary": "look up or signal processes based on name and other attributes",
            "Most Similar TLDR Script": "pkill -9 {{process_name}}",
            "Most Similar TLDR Task": "Kill all processes which match",
            "Top-3 Scripts": [
                "au_104903: pkill firefox",
                "ul_203869: pkill -u username",
                "su_220517: pkill -xf 'valgrind --tool=lackey ./testcases/kernel/syscalls/waitpid/waitpid03'"
            ],
            "Top-3 Similar Questions": [
                "au_104903: How do I kill processes in Ubuntu?",
                "ul_203869: Killall processes under a user?",
                "su_220517: How to kill a process with name having spaces?"
            ]
        },
        {
            "Command": "killall",
            "Explanations about Options": {
                "--user(M)": "Kill only processes the specified user owns. Command names are optional.",
                "-I(M)": "Do case insensitive process name match."
            },
            "MP Summary": "kill processes by name",
            "Most Similar TLDR Script": "killall -KILL {{process_name}}",
            "Most Similar TLDR Task": "Force kill a process",
            "Top-3 Scripts": [
                "au_104903: killall firefox",
                "ul_203869: killall --user name1",
                "au_926100: killall vlc"
            ],
            "Top-3 Similar Questions": [
                "au_104903: How do I kill processes in Ubuntu?",
                "ul_203869: Killall processes under a user?",
                "su_152514: Killing all processes of current user"
            ]
        },
        {
            "Command": "pidof",
            "Explanations about Options": {
                "-s(M)": "Single shot - this instructs the program to only return one pid."
            },
            "MP Summary": "find the process ID of a running program.",
            "Most Similar TLDR Script": "kill \"$(pidof {{name}})\"",
            "Most Similar TLDR Task": "Kill all processes with given name",
            "Top-3 Scripts": [
                "au_926100: kill $(pidof -s vlc)",
                "so_32926740: proid= pidof $proceso\n\nproid=$(pidof $proceso)"
            ],
            "Top-3 Similar Questions": [
                "au_926100: Kill Process Ubuntu 16.04",
                "so_32926740: How to kill a process by its pid in linux"
            ]
        },
        {
            "Command": "fuser",
            "Explanations about Options": {
                "--kill(M)": "Kill processes accessing the file. Unless changed with -SIGNAL, SIGKILL is sent.\n An fuser process never kills itself, but may kill other fuser processes. The\n effective user ID of the process executing fuser is set to its real user ID before\n attempting to kill.",
                "-k(M)": "Kill processes accessing the file. Unless changed with -SIGNAL, SIGKILL is sent.\n An fuser process never kills itself, but may kill other fuser processes. The\n effective user ID of the process executing fuser is set to its real user ID before\n attempting to kill."
            },
            "MP Summary": "identify processes using files or sockets",
            "Most Similar TLDR Script": "fuser --kill {{path/to/file_or_directory}}",
            "Most Similar TLDR Task": "Kill all processes accessing a file or directory (sends the `SIGKILL` signal)",
            "Top-3 Scripts": [
                "su_220517: fuser testcases/kernel/syscalls/waitpid/waitpid03\n\nfuser -k"
            ],
            "Top-3 Similar Questions": [
                "su_220517: How to kill a process with name having spaces?"
            ]
        },
        {
            "Command": "nohup",
            "Explanations about Options": {},
            "MP Summary": "run a command immune to hangups, with output to a non-tty",
            "Most Similar TLDR Script": "nohup {{command options}}",
            "Most Similar TLDR Task": "Run process that can live beyond the terminal",
            "Top-3 Scripts": [
                "ul_260584: #!/bin/sh\nnohup sxhkd </dev/null >/dev/null 2>/dev/null &\nnohup panel </dev/null >/dev/null 2>/dev/null &"
            ],
            "Top-3 Similar Questions": [
                "ul_260584: Kill command also kills other process"
            ]
        }
    ],
    "Query": "Kill all process of users in Ubuntu?"
}