{
  "Query": "Setting up FTP on Amazon Cloud Server",
  "Answers": [
    {
      "Command": "hostname",
      "MP Summary": "show or set the system's host name",
      "Most Similar TLDR Task": "Set current host name",
      "Most Similar TLDR Script": "hostname {{new_hostname}}",
      "Top-3 Similar Questions": [
        "au_134298: How do I set up Gitorious server on ubuntu?"
      ],
      "Top-3 Scripts": [
        "au_134298: repository_base_path should be /var/www/gitorious/repositories\ncookie_secret needs to be set to a random value >= 30 characters\ngitorious_client_port should be 80\ngitorious_host needs to be the exact hostname that clients will use (cookies get messed up otherwise)\narchive_cache_dir should be /var/www/gitorious/tarballs\narchive_work_dir should be something like /tmp/tarballs-work\nhide_http_clone_urls should be true (they require extra unknown setup to work)\nis_gitorious_dot_org should be false\nCreating the Gitorious database"
      ],
      "Explanations about Options": {}
    },
    {
      "Command": "a2ensite",
      "MP Summary": "enable or disable an apache2 site / virtual host",
      "Most Similar TLDR Task": "Enable a virtual host",
      "Most Similar TLDR Script": "sudo a2ensite {{virtual_host}}",
      "Top-3 Similar Questions": [
        "au_150340: How to set up a VirtualHost on Amazon EC2 for phpmyadmin",
        "au_463618: setting up subdomain on ubuntu server",
        "au_751389: Setting up multiple websites on a Linux server"
      ],
      "Top-3 Scripts": [
        "au_150340: sudo a2ensite test.example.com",
        "au_463618: sudo a2ensite subdomain.mydomain.com",
        "au_751389: a2ensite foo.com"
      ],
      "Explanations about Options": {}
    },
    {
      "Command": "ssh",
      "MP Summary": "OpenSSH SSH client (remote login program)",
      "Most Similar TLDR Task": "Connect to a remote server",
      "Most Similar TLDR Script": "ssh {{username}}@{{remote_host}}",
      "Top-3 Similar Questions": [
        "su_274934: Setting up ssh server on Ubuntu dektop",
        "so_6394762: How do I set up SSH access for an Amazon EC2 instance?",
        "au_143303: How do I set up a linux proxy for my mac"
      ],
      "Top-3 Scripts": [
        "su_274934: $ ssh <user>@<ssh server>\n\n/etc/ssh/sshd_config",
        "so_6394762: ssh -i /path/to/private-key root@<ec2-public-dns-address>",
        "au_143303: ssh -ND 1080 user@11.11.11.111 -p 22"
      ],
      "Explanations about Options": {
        "-N": "Do not execute a remote command. This is useful for just forwarding ports.",
        "-p": "Port to connect to on the remote host. This can be specified on a per-host basis in\n the configuration file."
      }
    },
    {
      "Command": "a2dissite",
      "MP Summary": "enable or disable an apache2 site / virtual host",
      "Most Similar TLDR Task": "Disable a virtual host",
      "Most Similar TLDR Script": "sudo a2dissite {{virtual_host}}",
      "Top-3 Similar Questions": [
        "au_134298: How do I set up Gitorious server on ubuntu?"
      ],
      "Top-3 Scripts": [
        "au_134298: a2dissite default && \\\n    a2dissite default-ssl && \\\n    a2ensite gitorious && \\\n    a2ensite gitorious-ssl"
      ],
      "Explanations about Options": {}
    },
    {
      "Command": "mysql",
      "MP Summary": "the MySQL command-line client",
      "Most Similar TLDR Task": "Connect to a database on another host",
      "Most Similar TLDR Script": "mysql -h {{database_host}} {{database_name}}",
      "Top-3 Similar Questions": [
        "au_134298: How do I set up Gitorious server on ubuntu?"
      ],
      "Top-3 Scripts": [
        "au_134298: mysql -u root -p"
      ],
      "Explanations about Options": {
        "-u": "The user name of the MySQL account to use for connecting to the server."
      }
    }
  ]
}