{
  "Query": "How do i select all text in Vi/Vim?",
  "Answers": [
    {
      "Command": "vim",
      "MP Summary": "Vi IMproved, a programmer's text editor",
      "Most Similar TLDR Task": "View Vim's help manual",
      "Most Similar TLDR Script": ":help<Enter>",
      "Top-3 Similar Questions": [
        "so_44541001: How do I select a specific block of text in vim?",
        "su_608292: Select vimenter autocmd's to run based on args",
        "ul_93208: How can I select all copy from vim and paste to other program e.g. mail client?"
      ],
      "Top-3 Scripts": [
        "so_44541001: ",
        "su_608292: vim --large\n\nvim -- . --large",
        "ul_93208: vim --version"
      ],
      "Explanations about Options": {
        "--version": "Print version information and exit."
      }
    },
    {
      "Command": "echo",
      "MP Summary": "display a line of text",
      "Most Similar TLDR Task": "Print a text message. Note: quotes are optional",
      "Most Similar TLDR Script": "echo \"{{Hello World}}\"",
      "Top-3 Similar Questions": [
        "so_2575545: Vim: Pipe selected text to shell cmd and receive output on vim info/command line",
        "so_45382472: bash select multiple answers at once",
        "so_55278978: How to select a specific range of rows from a text file with bash script"
      ],
      "Top-3 Scripts": [
        "so_2575545: function Test() range\n  echo system('echo '.shellescape(join(getline(a:firstline, a:lastline), \"\\n\")).'| pbcopy')\nendfunction",
        "so_45382472: ",
        "so_55278978: "
      ],
      "Explanations about Options": {}
    },
    {
      "Command": "sed",
      "MP Summary": "stream editor for filtering and transforming text",
      "Most Similar TLDR Task": "Replace only on lines matching the line pattern",
      "Most Similar TLDR Script": "sed '/{{line_pattern}}/s/{{find}}/{{replace}}/' {{filename}}",
      "Top-3 Similar Questions": [
        "so_45382472: bash select multiple answers at once",
        "so_27152909: Bash, selecting text surrounded by specific matches",
        "so_52951684: selecting random line from text file after deleting empty lines"
      ],
      "Top-3 Scripts": [
        "so_45382472: ",
        "so_27152909: sed -e '/\\$\\{10\\}/,/(\\{9\\}/!d' inputfile\n\nsed -ne '/\\$\\{10\\}/ {n;b c}; d;:c {/(\\{9\\}/ {d};p;n;b c}' inputfile",
        "so_52951684: sed '/^\\s*$/d' input.txt | shuf -n 1 >output.txt"
      ],
      "Explanations about Options": {
        "-e": "add the script to the commands to be executed"
      }
    },
    {
      "Command": "printf",
      "MP Summary": "format and print data",
      "Most Similar TLDR Task": "Print a text message",
      "Most Similar TLDR Script": "printf \"{{%s\\n}}\" \"{{Hello world}}\"",
      "Top-3 Similar Questions": [
        "so_24504838: Select text after two equal strings",
        "so_52194137: Select in loop don't ask for input"
      ],
      "Top-3 Scripts": [
        "so_24504838: awk 'NF==1{cmd=$1;next} NF==0{next} $1==cmd{printf \"%s\", $0; while (1) { if (! getline tmp) break; if(length(tmp)) printf \" %s\", tmp; else break;};print \"\"}' test.txt",
        "so_52194137: "
      ],
      "Explanations about Options": {}
    },
    {
      "Command": "read",
      "MP Summary": "read a line from standard input",
      "Most Similar TLDR Task": "Enable backspace and GNU readline hotkeys when entering input with read",
      "Most Similar TLDR Script": "read -e {{variable}}",
      "Top-3 Similar Questions": [
        "so_56048955: Select files reading names from a text file",
        "ul_171907: Use Netrw or Nerdtree in Zsh/Bash to select a file BY BROWSING?",
        "so_45382472: bash select multiple answers at once"
      ],
      "Top-3 Scripts": [
        "so_56048955: while read -r line; do find -type f -name \"*$line*\"; done < ../src_pdm3012/good_G20P1.txt",
        "ul_171907: ",
        "so_45382472: "
      ],
      "Explanations about Options": {}
    }
  ]
}