{
  "Query": "Any way to encode the url in curl command?",
  "Answers": [
    {
      "Command": "openssl",
      "MP Summary": "OpenSSL command line tool",
      "Top-3 Similar Questions": [
        "so_50631463: Why is base64 encoding my file on a Mac not resulting in a proper base64 string?"
      ],
      "Top-3 Scripts": [
        "so_50631463: openssl base64 -A -in myfile.binary -out ~/Downloads/myfile.base64"
      ],
      "Explanations about Options": {}
    },
    {
      "Command": "req",
      "MP Summary": "PKCS#10 certificate request and certificate generating utility",
      "Top-3 Similar Questions": [
        "so_62201134: Escaping multiple layers of mixed quotes for a curl command executed inside a bash script"
      ],
      "Top-3 Scripts": [
        "so_62201134: "
      ],
      "Explanations about Options": {}
    },
    {
      "Command": "ffmpeg",
      "MP Summary": "ffmpeg video converter",
      "Top-3 Similar Questions": [
        "su_1309487: ffmpeg encoding to convert video to PNGs, with subtitles",
        "su_774451: FFmpeg encoding part of the video with subtitles",
        "so_49287496: ffmpeg: concat and encode with one command"
      ],
      "Top-3 Scripts": [
        "su_1309487: ffmpeg -i file.mkv -r 1 -map 0:0 -vf \"subtitles=file.mkv\" images/output_%05d.png",
        "su_774451: ffmpeg -i \"path/to/input\" -ss 00:02:00 -t 30 -c:v libvpx -crf 5 -b:v 3M -c:a libvorbis -vf \"ass=path/ass\" \"output.webm\"",
        "so_49287496: ffmpeg -i 1.mp4 -c copy -video_track_timescale 25k 1_reset.mp4"
      ],
      "Explanations about Options": {
        "-vf": "Create the filtergraph specified by filtergraph and use it to filter the stream.",
        "-i": "input file url"
      }
    },
    {
      "Command": "base64",
      "MP Summary": "base64 encode/decode data and print to standard output",
      "Top-3 Similar Questions": [
        "so_27077101: Base 64 encoded output is different in java/shell",
        "so_50631463: Why is base64 encoding my file on a Mac not resulting in a proper base64 string?",
        "ul_447191: What's the right way to base64 encode a binary file on CentOS 7?"
      ],
      "Top-3 Scripts": [
        "so_27077101: echo dGVzdAo= | base64 --decode | od -c",
        "so_50631463: openssl base64 -A -in myfile.binary -out ~/Downloads/myfile.base64",
        "ul_447191: $ echo foo |base64 \nZm9vCg==\n$ echo foo |base64 |wc -c\n9\n\nbase64 -w0"
      ],
      "Explanations about Options": {
        "--decode": "decode data",
        "-i": "when decoding, ignore non-alphabet characters"
      }
    },
    {
      "Command": "base32",
      "MP Summary": "base32 encode/decode data and print to standard output",
      "Top-3 Similar Questions": [
        "tldr_5: Encode a file"
      ],
      "Top-3 Scripts": [
        "tldr_5: base32 {{filename}}"
      ],
      "Explanations about Options": {}
    }
  ]
}