{
  "Query": "How do I divide in the Linux console?",
  "Answers": [
    {
      "Command": "cp",
      "MP Summary": "copy files and directories",
      "Most Similar TLDR Task": "Copy a file to another location",
      "Most Similar TLDR Script": "cp {{path/to/source_file.ext}} {{path/to/target_file.ext}}",
      "Top-3 Similar Questions": [
        "so_30234984: dividing outputs in make by filename",
        "au_612131: How to display more than 1 terminal simultaneously"
      ],
      "Top-3 Scripts": [
        "so_30234984: %.output1: %.input\n    # If the stem that matched the '%' is equal to 'filename1'\n    if [ filename1 = '$*' ]; then\n        # Then copy the prerequisite/input file to the output file name.\n        cp $< $@\n    fi",
        "au_612131: cp /usr/share/applications/terminator.desktop ~/.local/share/applications/\nnano ~/.local/share/applications/terminator.desktop"
      ],
      "Explanations about Options": {}
    },
    {
      "Command": "echo",
      "MP Summary": "display a line of text",
      "Most Similar TLDR Task": "Print a message with environment variables",
      "Most Similar TLDR Script": "echo \"{{My path is $PATH}}\"",
      "Top-3 Similar Questions": [
        "so_13636663: Dividing per a lower number",
        "so_39343811: In bash how do I divide two variables and output the answer rounded upto 5 decimal digits?",
        "so_30398014: Divide two variables in bash"
      ],
      "Top-3 Scripts": [
        "so_13636663: set -o nounset                              # Treat unset variables as an error\ncount=1\nrtime=9\n\nuntil [ $count -eq $rtime ]\ndo\n    echo $(echo \"scale=2; $((count*10))/$rtime\" | bc)                                                                                 \n    sleep 1\n    count=$((count+1))\ndone",
        "so_39343811: $ echo \"scale=5; 12/7\" | bc\n1.71428\n\nsum=12\nn=7\noutput=$(echo \"scale=5;$sum/$n\" | bc)\necho \"$output\"\n\n$ sum=3345699\n$ n=1000000\n$ echo \"scale=5;($sum/$n)\" | bc\n3.34569\n\n$ printf \"%.5f\" \"$(echo \"scale=10;$sum/$n\" | bc)\"\n3.34570",
        "so_30398014: var1=8\nvar2=4\necho $((var1 / var2))\n\nvar1=3\nvar2=4\necho $((var1 / var2))\n\necho \"scale=2 ; $var1 / $var2\" | bc"
      ],
      "Explanations about Options": {}
    },
    {
      "Command": "import",
      "MP Summary": "saves any visible window on an X server and outputs it as an image file. You can capture a single window, the entire screen, or any rectangular portion of the screen.",
      "Most Similar TLDR Task": "Capture the entire X server screen in the PostScript image format",
      "Most Similar TLDR Script": "import -window root {{output.postscript}}",
      "Top-3 Similar Questions": [
        "ul_185305: Add every two consecutive lines in a column and divide it with the former and Print",
        "so_38677043: How to create own Linux console app?"
      ],
      "Top-3 Scripts": [
        "ul_185305: ",
        "so_38677043: #!/bin/python\n\n# hello.py\n\nfrom sys import argv\n\nname = argv[1]\nif name == 'bob':\n    print('hello', name)"
      ],
      "Explanations about Options": {}
    },
    {
      "Command": "convert",
      "MP Summary": "convert between image formats as well as resize an image, blur, crop, despeckle, dither, draw on, flip, join, re-sample, and much more.",
      "Most Similar TLDR Task": "Horizontally append images",
      "Most Similar TLDR Script": "convert {{image1.png}} {{image2.png}} {{image3.png}} +append {{image123.png}}",
      "Top-3 Similar Questions": [
        "au_143498: How to divide an image in X equal parts"
      ],
      "Top-3 Scripts": [
        "au_143498: convert -crop 20%x100% rose.jpg rose2.jpg"
      ],
      "Explanations about Options": {}
    },
    {
      "Command": "pdfposter",
      "MP Summary": "Scale and tile PDF images/pages to print on multiple pages.",
      "Most Similar TLDR Task": "Scale an A4 poster to A3 and then generate 2 A4 pages",
      "Most Similar TLDR Script": "pdfposter --scale 2 {{input_file.pdf}} {{output_file.pdf}}",
      "Top-3 Similar Questions": [
        "au_697091: Divide a A3 document in two A4 documents"
      ],
      "Top-3 Scripts": [
        "au_697091: sudo apt install pdfposter\npdfposter -s1 a3-input.pdf a4-output.pdf\n\nman pdfposter"
      ],
      "Explanations about Options": {}
    }
  ]
}