{
  "Query": "Recovered deleted files on Mac by command line",
  "Answers": [
    {
      "Command": "apt-get",
      "MP Summary": "APT package handling utility - command-line interface",
      "Most Similar TLDR Task": "Remove a package and its configuration files",
      "Most Similar TLDR Script": "apt-get purge {{package}}",
      "Top-3 Similar Questions": [
        "so_29693677: recover a removed fortran file if have executable",
        "au_319363: How to recover a file after deleting and merging multiple partitions?",
        "au_601457: Is it possible to recover a permemnantly deleted file on EXT partition?"
      ],
      "Top-3 Scripts": [
        "so_29693677: sudo apt-get install foremost",
        "au_319363: (sudo) apt-get install testdisk",
        "au_601457: sudo add-apt-repository ppa:teejee2008/ppa\nsudo apt-get update\nsudo apt-get install timeshift"
      ],
      "Explanations about Options": {}
    },
    {
      "Command": "xargs",
      "MP Summary": "build and execute command lines from standard input",
      "Most Similar TLDR Task": "Execute the command once for each input line, replacing any occurrences of the placeholder (here marked as `_`) with the input line",
      "Most Similar TLDR Script": "{{arguments_source}} | xargs -I _ {{command}} _ {{optional_extra_arguments}}",
      "Top-3 Similar Questions": [
        "so_33728181: how to delete a file recursively from folders on mac / unix",
        "ul_120287: How to recover from recursive 'chmod -x' on my home folder"
      ],
      "Top-3 Scripts": [
        "so_33728181: find parent_dir -name .DS_Store -print0 | xargs -0 rm -f",
        "ul_120287: "
      ],
      "Explanations about Options": {
        "-0": "Input items are terminated by a null character instead of by whitespace, and the\n quotes and backslash are not special (every character is taken literally).\n Disables the end of file string, which is treated like any other argument. Useful\n when input items might contain white space, quote marks, or backslashes. The GNU\n find -print0 option produces input suitable for this mode."
      }
    },
    {
      "Command": "echo",
      "MP Summary": "display a line of text",
      "Most Similar TLDR Task": "Append a message to the file",
      "Most Similar TLDR Script": "echo \"{{Hello World}}\" >> {{file.txt}}",
      "Top-3 Similar Questions": [
        "so_47857402: How to recover deleted file from FAT image?",
        "au_64812: Recover files without an extension after deleting them with a BASH command",
        "ul_120287: How to recover from recursive 'chmod -x' on my home folder"
      ],
      "Top-3 Scripts": [
        "so_47857402: $ echo \"hello world\" > NAME\n$ sudo cp -a NAME /mnt/fd\n$ ls -l /mnt/fd\ntotal 1\n-rwxr-xr-x  1 root root   12 Dec 17 13:55 NAME\n$ cat /mnt/fd/NAME\nhello world",
        "au_64812: ",
        "ul_120287: "
      ],
      "Explanations about Options": {}
    },
    {
      "Command": "photorec",
      "MP Summary": "Recover lost files from harddisk, digital camera and cdrom",
      "Most Similar TLDR Task": "Run PhotoRec on a specific device",
      "Most Similar TLDR Script": "sudo photorec {{/dev/sdb}}",
      "Top-3 Similar Questions": [
        "au_319363: How to recover a file after deleting and merging multiple partitions?"
      ],
      "Top-3 Scripts": [
        "au_319363: (sudo) photorec"
      ],
      "Explanations about Options": {}
    },
    {
      "Command": "extundelete",
      "MP Summary": "utility to undelete files from an ext3 or ext4 partition.",
      "Most Similar TLDR Task": "Restore all deleted files inside partition N on device X",
      "Most Similar TLDR Script": "sudo extundelete {{/dev/sdXN}} --restore-all",
      "Top-3 Similar Questions": [
        "ul_141646: Recover single file in the $HOME directory"
      ],
      "Top-3 Scripts": [
        "ul_141646: sudo extundelete ..."
      ],
      "Explanations about Options": {}
    }
  ]
}