{
  "Query": "How can I unlock a password locked rar file without knowing the password?",
  "Answers": [
    {
      "Command": "sudo",
      "Top-3 Similar Questions": [
        "ul_627102: Unlock ssh key on login",
        "ul_334634: Unlock user without giving a password for key usage",
        "au_906729: Revert password back to original"
      ],
      "Top-3 Scripts": [
        "ul_627102: sudo apt install keychain",
        "ul_334634: sudo -i\n\nsudo su -",
        "au_906729: sudo passwd <your username>"
      ]
    },
    {
      "Command": "passwd",
      "Top-3 Similar Questions": [
        "au_906729: Revert password back to original",
        "ul_264587: Permission denied after changing password (password is correct)",
        "su_589211: Can't unlock linux user account"
      ],
      "Top-3 Scripts": [
        "au_906729: sudo passwd <your username>",
        "su_589211: passwd -u",
        "au_1369184: sudo passwd"
      ]
    },
    {
      "Command": "to",
      "Top-3 Similar Questions": [
        "so_1754004: How to mask password in c?",
        "so_51000417: Command to Unlock a locked domain user",
        "au_1274185: SSH key-based login succeeds without unlocking private key, what gives?"
      ],
      "Top-3 Scripts": [
        "so_51000417: Search-ADAccount -LockedOut | \n    Select-Object -Property Name, sAMAccountName, DistinguishedName |\n        Format-Table\n$user = Read-Host -Prompt 'Enter user account (SAMACCOUNTNAME) to unlock or press ENTER to refresh list'\nSearch-ADAccount -LockedOut | \n    Where-Object -FilterScript {$_.samaccountname -eq $user} | \n        Unlock-ADAccount",
        "au_1274185: head -n 1 /path/to/private_key",
        "so_58534615: echo password | sudo -S rm /path/to/item"
      ]
    },
    {
      "Command": "ssh",
      "Top-3 Similar Questions": [
        "ul_193066: How to unlock account for public key ssh authorization, but not for password authorization?",
        "au_946190: ssh: Allow root to login without password",
        "ul_37633: Can a linux user change their password without knowing the current password?"
      ],
      "Top-3 Scripts": [
        "ul_193066: /etc/ssh/sshd_config",
        "au_946190: ssh root@server\n\nssh -i ~/.ssh/your_key root@server",
        "ul_37633: /etc/ssh/sshd_config"
      ]
    },
    {
      "Command": "dev",
      "Top-3 Similar Questions": [
        "ul_627102: Unlock ssh key on login",
        "su_1200726: How to unlock keyfile-protected partition where keyfile is located on a password protected partition?",
        "ul_161915: Change password on a LUKS filesystem without knowing the password"
      ],
      "Top-3 Scripts": [
        "ul_627102: if [ -z \"$TMUX\" ] ; then\n    keychain -q ~/.ssh/id_rsa;\nfi\n. ~/.keychain/$(hostname)-sh 2> /dev/null",
        "su_1200726: RESUME=/dev/mapper/lv_sdb3-lv_swap",
        "ul_161915: device=/dev/sda5\nvolume_name=foo\ncryptsetup luksAddKey $device --master-key-file <(dmsetup table --showkeys $volume_name | awk '{ print $5 }' | xxd -r -p)\n\n/dev/mapper"
      ]
    }
  ]
}