{
  "Query": "How do I remove a folder?",
  "Answers": [
    {
      "Command": "rm",
      "Top-3 Similar Questions": [
        "so_26345398: Remove folders Ubuntu",
        "au_35917: How to recursively remove .svn metadata folders?",
        "au_636086: how to remove a system protected folder"
      ],
      "Top-3 Scripts": [
        "so_26345398: rm -rf\n\nsudo rm -rf",
        "au_35917: find -type d -name '.svn' -exec rm -rfv {} \\;",
        "au_636086: sudo rm -r /usr/repo"
      ]
    },
    {
      "Command": "find",
      "Top-3 Similar Questions": [
        "au_1201615: Rename files and folders in all sub directorys to remove character",
        "so_60972205: Delete all files and folders recursively but excluding one folder",
        "au_35917: How to recursively remove .svn metadata folders?"
      ],
      "Top-3 Scripts": [
        "au_1201615: find path/to/start/dir/ -depth -name '*::*.*' -exec rename 's/:://' {} +",
        "so_60972205: find my-root-folder -mindepth 1 -not -path \"*/.git*\" -delete",
        "au_35917: find -type d -name '.svn' -exec rm -rfv {} \\;"
      ]
    },
    {
      "Command": "sudo",
      "Top-3 Similar Questions": [
        "so_26345398: Remove folders Ubuntu",
        "au_105627: How to remove unwanted configuration files/folders?",
        "au_636086: how to remove a system protected folder"
      ],
      "Top-3 Scripts": [
        "so_26345398: sudo rm -rf",
        "au_105627: sudo add-apt-repository ppa:tualatrix/ppa\nsudo apt-get update\nsudo apt-get install ubuntu-tweak",
        "au_636086: sudo rm -r /usr/repo"
      ]
    },
    {
      "Command": "apt-get",
      "Top-3 Similar Questions": [
        "au_105627: How to remove unwanted configuration files/folders?",
        "au_277838: Removing an Ubuntu installation",
        "au_705891: Accidentally removed Spotify folder, now I can't uninstall anything"
      ],
      "Top-3 Scripts": [
        "au_105627: sudo add-apt-repository ppa:tualatrix/ppa\nsudo apt-get update\nsudo apt-get install ubuntu-tweak",
        "au_277838: sudo apt-get update; sudo apt-get install -y os-uninstaller && os-uninstaller",
        "au_705891: sudo apt-get install -f --reinstall spotify-client\n\nsudo apt-get remove spotify-client"
      ]
    },
    {
      "Command": "folder",
      "Top-3 Similar Questions": [
        "so_61141044: Removing 'Empty' Folders",
        "so_51929442: Remove certain folders recursively?",
        "su_939397: Powershell: Dir /s - Remove Repeated Folders"
      ],
      "Top-3 Scripts": [
        "so_61141044: $Parent = 'D:\\MySuperCoolMusic'  # CHANGE THIS TO YOUR DESIRED FOLDER!!! #\n$Dirs = Get-ChildItem -Path $Parent -directory -Recurse\n\nforeach ($item in $Dirs) {   \n    if ((get-childitem $item.Fullname | measure-object | select -ExpandProperty count) -eq '0') {\n    write-verbose -Message \"The folder $($item.Fullname) is empty\" -Verbose\n\n    remove-item $item.Fullname -Verbose\n    }\n}\n\nremove-item -force -recurse -path \"c:\\whatever folder you want to remove\"",
        "su_939397: $folders = dir -s C:\\Users\\Name\\Downloads\\*.ttf | Select Directory -Unique\nforeach ($folder in $folders)\n{\n    echo $folder\n}",
        "so_18768445: find /path/to/folder -name \".git*\" -print0 | xargs -0 rm -rf"
      ]
    }
  ]
}