{
  "Query": "How do I set a custom resolution?",
  "Answers": [
    {
      "Command": "sudo",
      "Top-3 Similar Questions": [
        "au_18956: How to set resolution higher than maximum shown?",
        "au_515445: Nvidia x server setting no specific option",
        "au_682708: How to set a custom text highlighting colour"
      ],
      "Top-3 Scripts": [
        "au_18956: sudo apt-get purge fglrx\n\nsudo rm /etc/X11/xorg.conf",
        "au_515445: sudo gedit /etc/X11/xorg.conf",
        "au_682708: sudo nano \"/usr/share/themes/Numix Daily/gtk-3.0/gtk-dark.css\"\nsudo nano \"/usr/share/themes/Numix Daily/gtk-3.0/gtk.css\""
      ]
    },
    {
      "Command": "to",
      "Top-3 Similar Questions": [
        "tldr_1848: Set one or more semicolon-separated properties",
        "ul_541577: Defining Custom Location aliases",
        "tldr_1775: Set the import prefix string after 3rd-party packages (comma-separated list)"
      ],
      "Top-3 Scripts": [
        "tldr_1848: msbuild {{path/to/project_file}} /property:{{name=value}}",
        "ul_541577: export VIDFOLDER=/path/to/my/folder",
        "tldr_1775: goimports -local {{/path/to/package}} {{file}}.go"
      ]
    },
    {
      "Command": "xrandr",
      "Top-3 Similar Questions": [
        "su_347437: Xorg - how to specify a non-standard display resolution",
        "au_1075157: Unable to set my screen resolution higher",
        "ul_410688: Can't set correct display resolution"
      ],
      "Top-3 Scripts": [
        "su_347437: $ xrandr --newmode \"976x600_60.00\"   46.50  976 1016 1112 1248  600 603 613 624 -hsync +vsync\n\n$ xrandr --addmode LVDS1 976x600_60.00\n\n$ xrandr --output LVDS1 --mode 976x600_60.00 --set \"scaling mode\" Center\n\nxrandr --properties\n\nxrandr --query",
        "au_1075157: sudo xrandr --newmode \"1920x1080_60.00\"  173.00  1920 2048 2248 2576  1080 1083 1088 1120 -hsync +vsync\n\nsudo xrandr --addmode VGA-1 \"1920x1080_60.00\"\n\nxrandr --newmode \"1920x1080_60.00\"  173.00  1920 2048 2248 2576  1080 1083 1088 1120 -hsync +vsync\nxrandr --addmode VGA-1 \"1920x1080_60.00\"` and <kbd>ENTER</kbd> *(replace **VGA-1** with your display type (step 3) like **HDMI-1** or **DP-1**)*",
        "ul_410688: xrandr --newmode \"3840x2160x30.00\"  340.000000  3840 4080 4496 5152  2160 2164 2168 2200  -HSync +VSync\nxrandr --addmode HDMI-1 \"3840x2160x30.00\"\nxrandr --output HDMI-1 --mode \"3840x2160x30.00\""
      ]
    },
    {
      "Command": "cvt",
      "Top-3 Similar Questions": [
        "su_347437: Xorg - how to specify a non-standard display resolution",
        "au_1075157: Unable to set my screen resolution higher",
        "ul_387735: How to set a custom resolution with nvidia drivers installed?"
      ],
      "Top-3 Scripts": [
        "su_347437: $ cvt 976 600",
        "au_1075157: cvt 1920 1080",
        "ul_387735: cvt 1440 900 75"
      ]
    },
    {
      "Command": "and",
      "Top-3 Similar Questions": [
        "au_1075157: Unable to set my screen resolution higher",
        "au_605927: How do I set screen resolution for a specific program?",
        "su_530468: Powershell parameter set resolution with explicit parameter fails"
      ],
      "Top-3 Scripts": [
        "au_1075157: xrandr --newmode \"1920x1080_60.00\"  173.00  1920 2048 2248 2576  1080 1083 1088 1120 -hsync +vsync\nxrandr --addmode VGA-1 \"1920x1080_60.00\"` and <kbd>ENTER</kbd> *(replace **VGA-1** with your display type (step 3) like **HDMI-1** or **DP-1**)*"
      ]
    }
  ]
}