{
  "Query": "Changing Network Interfaces name Ubuntu 16.04",
  "Answers": [
    {
      "Command": "sudo",
      "Top-3 Similar Questions": [
        "au_1255823: Network Interface names change every reboot",
        "au_1292392: How to change distribution name (20.04)",
        "au_1178486: Change computer name Ubuntu"
      ],
      "Top-3 Scripts": [
        "au_1255823: sudo pico /etc/default/grub\n\nsudo update-grub\n\nsudo lshw -C network",
        "au_1292392: sudo dpkg-divert --add  /usr/lib/os-release",
        "au_1178486: sudo hostnamectl | grep hostname\n\nsudo hostnamectl set-hostname whatever\n\nsudo passwd root"
      ]
    },
    {
      "Command": "nano",
      "Top-3 Similar Questions": [
        "au_771910: How to force old wlan naming 16.04",
        "au_498018: How to change the DNS server across network interfaces?",
        "au_690511: How to change DNS in Ubuntu 15.10?"
      ],
      "Top-3 Scripts": [
        "au_771910: nano /etc/udev/rules.d/10-network.rules",
        "au_498018: sudo nano /etc/resolvconf/resolv.conf.d/base",
        "au_690511: sudo nano /etc/NetworkManager/NetworkManager.conf\n\n[main]\nplugins=ifupdown,keyfile,ofono\n#dns=dnsmasq\n\nsudo rm -f /etc/resolv.conf  # Delete the symbolic link\nsudo nano /etc/resolv.conf   # Create static file\n\n# Content of static resolv.conf\nnameserver 208.67.220.220\nnameserver 208.67.220.222"
      ]
    },
    {
      "Command": "install",
      "Top-3 Similar Questions": [
        "au_916013: How to change Wake-on Lan settings?",
        "au_762764: Cannot change brightness (Ubuntu 16.04 LTS, Unity)",
        "au_534881: How to change the color interface of Ubuntu?"
      ],
      "Top-3 Scripts": [
        "au_916013: sudo apt install ethtool",
        "au_762764: sudo apt install brightness-controller\n\nsudo apt install brightness-controller-simple",
        "au_534881: sudo apt-get install gnome-tweak-tool"
      ]
    },
    {
      "Command": "dev",
      "Top-3 Similar Questions": [
        "ul_570893: Change interface name",
        "au_595140: Lubuntu 14.04.2 change network configuration using terminal",
        "au_509975: How can I change the network configuration on Ubuntu 14.04 server?"
      ],
      "Top-3 Scripts": [
        "ul_570893: sudo  ln -s /dev/null /etc/udev/rules.d/70-net-setup-link.rules",
        "au_595140: ip addr flush dev eth0\nifdown --exclude=lo -a && ifup --exclude=lo -a\n\nip addr flush dev eth0 && ifdown --exclude=lo -a && ifup --exclude=lo -a",
        "au_509975: ifdown {device}\nip addr flush dev {device}\nifup {device}"
      ]
    },
    {
      "Command": "ip",
      "Top-3 Similar Questions": [
        "au_595140: Lubuntu 14.04.2 change network configuration using terminal",
        "au_509975: How can I change the network configuration on Ubuntu 14.04 server?",
        "au_1204412: Changing the network interface for specific user?"
      ],
      "Top-3 Scripts": [
        "au_595140: ip addr flush dev eth0\nifdown --exclude=lo -a && ifup --exclude=lo -a\n\nip addr flush dev eth0 && ifdown --exclude=lo -a && ifup --exclude=lo -a",
        "au_509975: ifdown {device}\nip addr flush dev {device}\nifup {device}",
        "au_1204412: ip route add table 10 your_route_for_that_user\n\nip rule add fwmark 15 table 10"
      ]
    }
  ]
}